LICENSE
MANIFEST.in
README.md
setup.py
django_flexible_permissions.egg-info/PKG-INFO
django_flexible_permissions.egg-info/SOURCES.txt
django_flexible_permissions.egg-info/dependency_links.txt
django_flexible_permissions.egg-info/pbr.json
django_flexible_permissions.egg-info/top_level.txt
flexible_permissions/__init__.py
flexible_permissions/_utils.py
flexible_permissions/agents.py
flexible_permissions/mixins.py
flexible_permissions/models.py
flexible_permissions/query.py
flexible_permissions/relations.py
flexible_permissions/roles.py
flexible_permissions/shortcuts.py
flexible_permissions/migrations/0001_initial.py
flexible_permissions/migrations/__init__.py